wework_callback/WXBizMsgCrypt3.py
wework_callback/__init__.py
wework_callback/ierror.py
wework_callback_json/Sample.py
wework_callback_json/WXBizJsonMsgCrypt.py
wework_callback_json/__init__.py
wework_callback_json/ierror.py
wework_sendmsg/__init__.py
wework_sendmsg/sendmsg.py
weworkapi/AbstractApi.py
weworkapi/CorpApi.py
weworkapi/ServiceCorpApi.py
weworkapi/ServiceProviderApi.py
weworkapi/__init__.py
weworkapi_cfomp-1.1.5.dist-info/METADATA
weworkapi_cfomp-1.1.5.dist-info/WHEEL
weworkapi_cfomp-1.1.5.dist-info/entry_points.txt
weworkapi_cfomp-1.1.5.dist-info/top_level.txt
weworkapi_cfomp-1.1.5.dist-info/RECORD
