Metadata-Version: 2.1
Name: weworkapi-cfomp
Version: 1.1.5
Summary: wework server side api
Author: chenhp
Author-email: chenhp@shchinafortune.com
Requires-Dist: requests
Requires-Dist: pycryptodome
Requires-Dist: PyYAML
Requires-Dist: flatten-dict
Requires-Dist: dict-recursive-update
